relativity/__init__.py
relativity/relativity.py
relativity/star.py
relativity/tree.py
relativity/tests/__init__.py
relativity/tests/test_basic.py
relativity/tests/test_perf.py
relativity/tests/test_star.py
relativity/tests/test_tree.py
relativity-20.1.0.dist-info/LICENSE
relativity-20.1.0.dist-info/METADATA
relativity-20.1.0.dist-info/WHEEL
relativity-20.1.0.dist-info/top_level.txt
relativity-20.1.0.dist-info/RECORD
